Metadata-Version: 2.4
Name: mhcflurry
Version: 2.1.5
Summary: MHC Binding Predictor
Home-page: https://github.com/openvax/mhcflurry
Author: Tim O'Donnell and Alex Rubinsteyn
Author-email: timodonnell@gmail.com
License: http://www.apache.org/licenses/LICENSE-2.0.html
Classifier: Development Status :: 5 - Production/Stable
Classifier: Environment :: Console
Classifier: Operating System :: OS Independent
Classifier: Intended Audience :: Science/Research
Classifier: License :: OSI Approved :: Apache Software License
Classifier: Programming Language :: Python
Classifier: Topic :: Scientific/Engineering :: Bio-Informatics
License-File: LICENSE
Requires-Dist: six
Requires-Dist: pandas>=0.20.3
Requires-Dist: appdirs
Requires-Dist: scikit-learn
Requires-Dist: mhcgnomes>=0.8.4
Requires-Dist: numpy
Requires-Dist: pyyaml
Requires-Dist: tqdm
Requires-Dist: tensorflow>=2.15.0
Requires-Dist: tf-keras
Dynamic: author
Dynamic: author-email
Dynamic: classifier
Dynamic: description
Dynamic: description-content-type
Dynamic: home-page
Dynamic: license
Dynamic: license-file
Dynamic: requires-dist
Dynamic: summary
